{"cameraMode":{"drawMode":0,"name":"Shaded","section":"Shading Mode"},"sceneLighting":true,"audioPlay":false,"sceneViewState":{"m_AlwaysRefresh":false,"showFog":true,"showSkybox":true,"showFlares":true,"showImageEffects":true,"showParticleSystems":true,"showVisualEffectGraphs":true,"m_FxEnabled":true},"in2DMode":false,"pivot":{"x":3.5707314014434816,"y":4.554224014282227,"z":-12.382726669311524},"rotation":{"x":0.038813892751932147,"y":-0.8817363977432251,"z":0.4644627869129181,"w":0.07410810887813568},"size":10.0,"orthographic":false}