{"cameraMode":{"drawMode":0,"name":"Shaded","section":"Shading Mode"},"sceneLighting":false,"audioPlay":false,"sceneViewState":{"m_AlwaysRefresh":false,"showFog":true,"showSkybox":false,"showFlares":true,"showImageEffects":true,"showParticleSystems":true,"showVisualEffectGraphs":true,"m_FxEnabled":true},"in2DMode":false,"pivot":{"x":16.894577026367189,"y":-29.173093795776368,"z":-4.982768535614014},"rotation":{"x":-0.26078128814697268,"y":-0.7352640628814697,"z":0.3942630887031555,"w":-0.48591673374176028},"size":21.0319766998291,"orthographic":false}